{
  "tomorrow": "2022-11-28T12:05:05.604872426-05:00",
  "city": "Ottawa",
  "data": [
    {
      "name": "WeatherApi",
      "snaps": [
        {
          "fog": false,
          "time": 1669611600,
          "temperature": 2.3888888888888875,
          "windSpeed": 8.3,
          "gusts": 11.2,
          "pressure": 995,
          "humidity": 96,
          "dewPoint": 1.7777777777777795,
          "cloudCover": 100,
          "visibility": 9
        },
        {
          "fog": false,
          "time": 1669615200,
          "temperature": 2.2222222222222223,
          "windSpeed": 7.9,
          "gusts": 10.4,
          "pressure": 994,
          "humidity": 94,
          "dewPoint": 1.3888888888888888,
          "cloudCover": 100,
          "visibility": 9
        },
        {
          "fog": false,
          "time": 1669618800,
          "temperature": 2.1111111111111094,
          "windSpeed": 11.2,
          "gusts": 15.1,
          "pressure": 995,
          "humidity": 93,
          "dewPoint": 1.1111111111111112,
          "cloudCover": 100,
          "visibility": 6
        },
        {
          "fog": false,
          "time": 1669622400,
          "temperature": 2.1111111111111094,
          "windSpeed": 14.4,
          "gusts": 19.4,
          "pressure": 997,
          "humidity": 93,
          "dewPoint": 1.1111111111111112,
          "cloudCover": 100,
          "visibility": 10
        },
        {
          "fog": false,
          "time": 1669626000,
          "temperature": 2.000000000000001,
          "windSpeed": 15.8,
          "gusts": 21.2,
          "pressure": 998,
          "humidity": 91,
          "dewPoint": 0.7222222222222207,
          "cloudCover": 100,
          "visibility": 10
        },
        {
          "fog": false,
          "time": 1669629600,
          "temperature": 1.7777777777777795,
          "windSpeed": 16.9,
          "gusts": 22,
          "pressure": 999,
          "humidity": 88,
          "dewPoint": 0,
          "cloudCover": 79,
          "visibility": 10
        },
        {
          "fog": false,
          "time": 1669633200,
          "temperature": 1.2222222222222239,
          "windSpeed": 20.9,
          "gusts": 27.7,
          "pressure": 1001,
          "humidity": 85,
          "dewPoint": -1.0000000000000004,
          "cloudCover": 59,
          "visibility": 10
        },
        {
          "fog": false,
          "time": 1669636800,
          "temperature": 0.2777777777777778,
          "windSpeed": 19.8,
          "gusts": 26.3,
          "pressure": 1004,
          "humidity": 85,
          "dewPoint": -2.000000000000001,
          "cloudCover": 46,
          "visibility": 10
        },
        {
          "fog": false,
          "time": 1669640400,
          "temperature": -0.11111111111111072,
          "windSpeed": 18.7,
          "gusts": 25.2,
          "pressure": 1005,
          "humidity": 82,
          "dewPoint": -2.7777777777777777,
          "cloudCover": 34,
          "visibility": 10
        },
        {
          "fog": false,
          "time": 1669644000,
          "temperature": -0.2777777777777778,
          "windSpeed": 18.4,
          "gusts": 25.2,
          "pressure": 1006,
          "humidity": 79,
          "dewPoint": -3.5000000000000004,
          "cloudCover": 45,
          "visibility": 10
        }
      ],
      "sunrise": "2022-11-28T07:19:00-05:00"
    }
  ]
}