{
  "tomorrow": "2023-05-19T12:05:08.489078771-04:00",
  "city": "Ottawa",
  "data": [
    {
      "name": "WeatherApi",
      "snaps": [
        {
          "fog": false,
          "time": 1684468800,
          "temperature": 3.611111111111111,
          "windSpeed": 6.8,
          "gusts": 14.4,
          "pressure": 1022,
          "humidity": 64,
          "dewPoint": -2.6111111111111107,
          "cloudCover": 12,
          "visibility": 10
        },
        {
          "fog": false,
          "time": 1684472400,
          "temperature": 3.2222222222222205,
          "windSpeed": 6.5,
          "gusts": 13.7,
          "pressure": 1022,
          "humidity": 67,
          "dewPoint": -2.2222222222222223,
          "cloudCover": 6,
          "visibility": 10
        },
        {
          "fog": false,
          "time": 1684476000,
          "temperature": 3.111111111111112,
          "windSpeed": 5.8,
          "gusts": 12.2,
          "pressure": 1022,
          "humidity": 71,
          "dewPoint": -1.6111111111111103,
          "cloudCover": 5,
          "visibility": 10
        },
        {
          "fog": false,
          "time": 1684479600,
          "temperature": 2.8888888888888906,
          "windSpeed": 6.1,
          "gusts": 13,
          "pressure": 1021,
          "humidity": 76,
          "dewPoint": -0.777777777777777,
          "cloudCover": 5,
          "visibility": 10
        },
        {
          "fog": false,
          "time": 1684483200,
          "temperature": 2.6111111111111125,
          "windSpeed": 7.2,
          "gusts": 15.1,
          "pressure": 1021,
          "humidity": 81,
          "dewPoint": -0.3888888888888885,
          "cloudCover": 5,
          "visibility": 10
        },
        {
          "fog": false,
          "time": 1684486800,
          "temperature": 2.6111111111111125,
          "windSpeed": 6.8,
          "gusts": 14.4,
          "pressure": 1021,
          "humidity": 84,
          "dewPoint": 0.22222222222222143,
          "cloudCover": 5,
          "visibility": 10
        },
        {
          "fog": false,
          "time": 1684490400,
          "temperature": 3.3888888888888897,
          "windSpeed": 7.2,
          "gusts": 15.1,
          "pressure": 1020,
          "humidity": 86,
          "dewPoint": 1.2222222222222239,
          "cloudCover": 6,
          "visibility": 10
        },
        {
          "fog": false,
          "time": 1684494000,
          "temperature": 6.111111111111111,
          "windSpeed": 7.2,
          "gusts": 13.3,
          "pressure": 1020,
          "humidity": 82,
          "dewPoint": 3.2222222222222205,
          "cloudCover": 8,
          "visibility": 10
        },
        {
          "fog": false,
          "time": 1684497600,
          "temperature": 9.777777777777779,
          "windSpeed": 14.4,
          "gusts": 20.5,
          "pressure": 1020,
          "humidity": 80,
          "dewPoint": 6.611111111111111,
          "cloudCover": 26,
          "visibility": 10
        },
        {
          "fog": false,
          "time": 1684501200,
          "temperature": 13.11111111111111,
          "windSpeed": 22.3,
          "gusts": 28.1,
          "pressure": 1020,
          "humidity": 73,
          "dewPoint": 8.38888888888889,
          "cloudCover": 55,
          "visibility": 10
        }
      ],
      "sunrise": "2023-05-19T05:29:00-04:00"
    }
  ]
}